pspark/__init__.py
pspark/abstract_pspark.py
pspark/constants.py
pspark/pspark.py
pspark/pspark_async.py
pspark/pspark_s2s.py
pspark/enums/__init__.py
pspark/enums/api_url.py
pspark/enums/api_version.py
pspark/enums/http_method.py
pspark/exceptions/__init__.py
pspark/exceptions/http_client_exception.py
pspark/exceptions/http_exception.py
pspark/exceptions/http_redirect_exception.py
pspark/exceptions/http_server_exception.py
pspark/exceptions/http_timeout_exception.py
pspark/exceptions/response_validation_exception.py
pspark/helpers/__init__.py
pspark/helpers/request_helper.py
pspark/http_client_wrappers/__init__.py
pspark/http_client_wrappers/abstract_http_client_wrapper.py
pspark/http_client_wrappers/httpx_async_wrapper.py
pspark/http_client_wrappers/httpx_sync_wrapper.py
pspark/requests/__init__.py
pspark/requests/abstract_request.py
pspark/requests/address_request.py
pspark/requests/balance_request.py
pspark/requests/balances_request.py
pspark/requests/details.py
pspark/requests/invoice_request.py
pspark/requests/rates_request.py
pspark/requests/transaction_request.py
pspark/requests/withdrawal_request.py
pspark/requests/details_dto/__init__.py
pspark/requests/details_dto/bank.py
pspark/requests/details_dto/billing_info.py
pspark/requests/details_dto/card_data.py
pspark/requests/details_dto/crypto.py
pspark/requests/details_dto/customer.py
pspark/requests/details_dto/escrow_payment.py
pspark/requests/details_dto/project.py
pspark/requests/details_dto/ui.py
pspark/requests/details_dto/web_data.py
pspark/responces/__init__.py
pspark/responces/http_response.py
pspark/validators/__init__.py
pspark/validators/url_validator.py
pspark_sdk-0.0.17.dist-info/licenses/LICENSE
pspark_sdk-0.0.17.dist-info/METADATA
pspark_sdk-0.0.17.dist-info/WHEEL
pspark_sdk-0.0.17.dist-info/top_level.txt
pspark_sdk-0.0.17.dist-info/RECORD
