Metadata-Version: 2.4
Name: pspark-sdk
Version: 0.0.17
Summary: Python SDK for merchant REST API
Author: PSPark
License: The MIT License (MIT)
Project-URL: Homepage, https://github.com/ps-park/sdk-python
Requires-Python: >=3.8.0
License-File: LICENSE
Requires-Dist: httpx
Requires-Dist: python-jose[cryptography]
Dynamic: license-file
